{"frames": {

"Collectable.png":
{
	"frame": {"x":2,"y":2,"w":55,"h":55},
	"rotated": false,
	"trimmed": false,
	"spriteSourceSize": {"x":0,"y":0,"w":55,"h":55},
	"sourceSize": {"w":55,"h":55},
	"pivot": {"x":0.5,"y":0.5}
},
"Collectable_ghost.png":
{
	"frame": {"x":59,"y":2,"w":55,"h":55},
	"rotated": false,
	"trimmed": false,
	"spriteSourceSize": {"x":0,"y":0,"w":55,"h":55},
	"sourceSize": {"w":55,"h":55},
	"pivot": {"x":0.5,"y":0.5}
},
"CheckPoint.png":
{
	"frame": {"x":116,"y":2,"w":38,"h":90},
	"rotated": false,
	"trimmed": false,
	"spriteSourceSize": {"x":0,"y":0,"w":38,"h":90},
	"sourceSize": {"w":38,"h":90},
	"pivot": {"x":0.5,"y":0.5}
},
"CheckPoint_used.png":
{
	"frame": {"x":156,"y":2,"w":38,"h":90},
	"rotated": false,
	"trimmed": false,
	"spriteSourceSize": {"x":0,"y":0,"w":38,"h":90},
	"sourceSize": {"w":38,"h":90},
	"pivot": {"x":0.5,"y":0.5}
},
"KillZoneStatic0011.png":
{
	"frame": {"x":196,"y":2,"w":105,"h":46},
	"rotated": false,
	"trimmed": false,
	"spriteSourceSize": {"x":0,"y":0,"w":105,"h":46},
	"sourceSize": {"w":105,"h":46},
	"pivot": {"x":0.5,"y":0.5}
},
"KillZoneStatic0012.png":
{
	"frame": {"x":196,"y":2,"w":105,"h":46},
	"rotated": false,
	"trimmed": false,
	"spriteSourceSize": {"x":0,"y":0,"w":105,"h":46},
	"sourceSize": {"w":105,"h":46},
	"pivot": {"x":0.5,"y":0.5}
},
"KillZoneStatic0013.png":
{
	"frame": {"x":196,"y":2,"w":105,"h":46},
	"rotated": false,
	"trimmed": false,
	"spriteSourceSize": {"x":0,"y":0,"w":105,"h":46},
	"sourceSize": {"w":105,"h":46},
	"pivot": {"x":0.5,"y":0.5}
},
"KillZoneStatic0004.png":
{
	"frame": {"x":303,"y":2,"w":105,"h":46},
	"rotated": false,
	"trimmed": false,
	"spriteSourceSize": {"x":0,"y":0,"w":105,"h":46},
	"sourceSize": {"w":105,"h":46},
	"pivot": {"x":0.5,"y":0.5}
},
"KillZoneStatic0005.png":
{
	"frame": {"x":303,"y":2,"w":105,"h":46},
	"rotated": false,
	"trimmed": false,
	"spriteSourceSize": {"x":0,"y":0,"w":105,"h":46},
	"sourceSize": {"w":105,"h":46},
	"pivot": {"x":0.5,"y":0.5}
},
"KillZoneStatic0001.png":
{
	"frame": {"x":410,"y":2,"w":105,"h":46},
	"rotated": false,
	"trimmed": false,
	"spriteSourceSize": {"x":0,"y":0,"w":105,"h":46},
	"sourceSize": {"w":105,"h":46},
	"pivot": {"x":0.5,"y":0.5}
},
"KillZoneStatic0002.png":
{
	"frame": {"x":410,"y":2,"w":105,"h":46},
	"rotated": false,
	"trimmed": false,
	"spriteSourceSize": {"x":0,"y":0,"w":105,"h":46},
	"sourceSize": {"w":105,"h":46},
	"pivot": {"x":0.5,"y":0.5}
},
"KillZoneStatic0003.png":
{
	"frame": {"x":410,"y":2,"w":105,"h":46},
	"rotated": false,
	"trimmed": false,
	"spriteSourceSize": {"x":0,"y":0,"w":105,"h":46},
	"sourceSize": {"w":105,"h":46},
	"pivot": {"x":0.5,"y":0.5}
},
"KillZoneStatic0009.png":
{
	"frame": {"x":517,"y":2,"w":105,"h":46},
	"rotated": false,
	"trimmed": false,
	"spriteSourceSize": {"x":0,"y":0,"w":105,"h":46},
	"sourceSize": {"w":105,"h":46},
	"pivot": {"x":0.5,"y":0.5}
},
"KillZoneStatic0010.png":
{
	"frame": {"x":517,"y":2,"w":105,"h":46},
	"rotated": false,
	"trimmed": false,
	"spriteSourceSize": {"x":0,"y":0,"w":105,"h":46},
	"sourceSize": {"w":105,"h":46},
	"pivot": {"x":0.5,"y":0.5}
},
"KillZoneStatic0014.png":
{
	"frame": {"x":624,"y":2,"w":105,"h":46},
	"rotated": false,
	"trimmed": false,
	"spriteSourceSize": {"x":0,"y":0,"w":105,"h":46},
	"sourceSize": {"w":105,"h":46},
	"pivot": {"x":0.5,"y":0.5}
},
"KillZoneStatic0015.png":
{
	"frame": {"x":624,"y":2,"w":105,"h":46},
	"rotated": false,
	"trimmed": false,
	"spriteSourceSize": {"x":0,"y":0,"w":105,"h":46},
	"sourceSize": {"w":105,"h":46},
	"pivot": {"x":0.5,"y":0.5}
},
"KillZoneStatic0006.png":
{
	"frame": {"x":731,"y":2,"w":105,"h":46},
	"rotated": false,
	"trimmed": false,
	"spriteSourceSize": {"x":0,"y":0,"w":105,"h":46},
	"sourceSize": {"w":105,"h":46},
	"pivot": {"x":0.5,"y":0.5}
},
"KillZoneStatic0007.png":
{
	"frame": {"x":731,"y":2,"w":105,"h":46},
	"rotated": false,
	"trimmed": false,
	"spriteSourceSize": {"x":0,"y":0,"w":105,"h":46},
	"sourceSize": {"w":105,"h":46},
	"pivot": {"x":0.5,"y":0.5}
},
"KillZoneStatic0008.png":
{
	"frame": {"x":731,"y":2,"w":105,"h":46},
	"rotated": false,
	"trimmed": false,
	"spriteSourceSize": {"x":0,"y":0,"w":105,"h":46},
	"sourceSize": {"w":105,"h":46},
	"pivot": {"x":0.5,"y":0.5}
},
"KillZoneDynamic.png":
{
	"frame": {"x":838,"y":2,"w":92,"h":92},
	"rotated": false,
	"trimmed": false,
	"spriteSourceSize": {"x":0,"y":0,"w":92,"h":92},
	"sourceSize": {"w":92,"h":92},
	"pivot": {"x":0.5,"y":0.5}
},
"Wall0.png":
{
	"frame": {"x":2,"y":96,"w":105,"h":105},
	"rotated": false,
	"trimmed": false,
	"spriteSourceSize": {"x":0,"y":0,"w":105,"h":105},
	"sourceSize": {"w":105,"h":105},
	"pivot": {"x":0.5,"y":0.5}
},
"Platform0.png":
{
	"frame": {"x":109,"y":96,"w":158,"h":79},
	"rotated": false,
	"trimmed": false,
	"spriteSourceSize": {"x":0,"y":0,"w":158,"h":79},
	"sourceSize": {"w":158,"h":79},
	"pivot": {"x":0.5,"y":0.5}
},
"BridgeLeft.png":
{
	"frame": {"x":269,"y":96,"w":131,"h":131},
	"rotated": false,
	"trimmed": false,
	"spriteSourceSize": {"x":0,"y":0,"w":131,"h":131},
	"sourceSize": {"w":131,"h":131},
	"pivot": {"x":0.5,"y":0.5}
},
"BridgeRight.png":
{
	"frame": {"x":402,"y":96,"w":131,"h":131},
	"rotated": false,
	"trimmed": false,
	"spriteSourceSize": {"x":0,"y":0,"w":131,"h":131},
	"sourceSize": {"w":131,"h":131},
	"pivot": {"x":0.5,"y":0.5}
},
"Destructible.png":
{
	"frame": {"x":535,"y":96,"w":158,"h":158},
	"rotated": false,
	"trimmed": false,
	"spriteSourceSize": {"x":0,"y":0,"w":158,"h":158},
	"sourceSize": {"w":158,"h":158},
	"pivot": {"x":0.5,"y":0.5}
},
"Platform1.png":
{
	"frame": {"x":695,"y":96,"w":263,"h":79},
	"rotated": false,
	"trimmed": false,
	"spriteSourceSize": {"x":0,"y":0,"w":263,"h":79},
	"sourceSize": {"w":263,"h":79},
	"pivot": {"x":0.5,"y":0.5}
},
"Wall3.png":
{
	"frame": {"x":2,"y":256,"w":210,"h":210},
	"rotated": false,
	"trimmed": false,
	"spriteSourceSize": {"x":0,"y":0,"w":210,"h":210},
	"sourceSize": {"w":210,"h":210},
	"pivot": {"x":0.5,"y":0.5}
},
"LimitRight.png":
{
	"frame": {"x":214,"y":256,"w":210,"h":210},
	"rotated": false,
	"trimmed": false,
	"spriteSourceSize": {"x":0,"y":0,"w":210,"h":210},
	"sourceSize": {"w":210,"h":210},
	"pivot": {"x":0.5,"y":0.5}
},
"Ground.png":
{
	"frame": {"x":426,"y":256,"w":210,"h":213},
	"rotated": false,
	"trimmed": false,
	"spriteSourceSize": {"x":0,"y":0,"w":210,"h":213},
	"sourceSize": {"w":210,"h":213},
	"pivot": {"x":0.5,"y":0.5}
},
"LimitLeft.png":
{
	"frame": {"x":638,"y":256,"w":236,"h":210},
	"rotated": false,
	"trimmed": false,
	"spriteSourceSize": {"x":0,"y":0,"w":236,"h":210},
	"sourceSize": {"w":236,"h":210},
	"pivot": {"x":0.5,"y":0.5}
},
"Wall1.png":
{
	"frame": {"x":2,"y":471,"w":263,"h":184},
	"rotated": false,
	"trimmed": false,
	"spriteSourceSize": {"x":0,"y":0,"w":263,"h":184},
	"sourceSize": {"w":263,"h":184},
	"pivot": {"x":0.5,"y":0.5}
},
"Wall2.png":
{
	"frame": {"x":267,"y":471,"w":473,"h":184},
	"rotated": false,
	"trimmed": false,
	"spriteSourceSize": {"x":0,"y":0,"w":473,"h":184},
	"sourceSize": {"w":473,"h":184},
	"pivot": {"x":0.5,"y":0.5}
}},
"meta": {
	"app": "http://www.codeandweb.com/texturepacker",
	"version": "1.0",
	"image": "decor_graphics.png",
	"format": "RGBA8888",
	"size": {"w":960,"h":657},
	"scale": "1",
	"smartupdate": "$TexturePacker:SmartUpdate:d63fa8ceb07dc5e7e4cae3888d6d8264:9155a80a795a9f3299804944d0aa88f1:2c5c4d4df6c539f1635c92a1609ba10f$"
}
}
