{"frames": {

"KillZoneStatic0001.png":
{
	"frame": {"x":2,"y":2,"w":70,"h":31},
	"rotated": false,
	"trimmed": false,
	"spriteSourceSize": {"x":0,"y":0,"w":70,"h":31},
	"sourceSize": {"w":70,"h":31},
	"pivot": {"x":0.5,"y":0.5}
},
"KillZoneStatic0002.png":
{
	"frame": {"x":2,"y":2,"w":70,"h":31},
	"rotated": false,
	"trimmed": false,
	"spriteSourceSize": {"x":0,"y":0,"w":70,"h":31},
	"sourceSize": {"w":70,"h":31},
	"pivot": {"x":0.5,"y":0.5}
},
"KillZoneStatic0003.png":
{
	"frame": {"x":2,"y":2,"w":70,"h":31},
	"rotated": false,
	"trimmed": false,
	"spriteSourceSize": {"x":0,"y":0,"w":70,"h":31},
	"sourceSize": {"w":70,"h":31},
	"pivot": {"x":0.5,"y":0.5}
},
"KillZoneStatic0004.png":
{
	"frame": {"x":74,"y":2,"w":70,"h":31},
	"rotated": false,
	"trimmed": false,
	"spriteSourceSize": {"x":0,"y":0,"w":70,"h":31},
	"sourceSize": {"w":70,"h":31},
	"pivot": {"x":0.5,"y":0.5}
},
"KillZoneStatic0005.png":
{
	"frame": {"x":74,"y":2,"w":70,"h":31},
	"rotated": false,
	"trimmed": false,
	"spriteSourceSize": {"x":0,"y":0,"w":70,"h":31},
	"sourceSize": {"w":70,"h":31},
	"pivot": {"x":0.5,"y":0.5}
},
"KillZoneStatic0009.png":
{
	"frame": {"x":146,"y":2,"w":70,"h":31},
	"rotated": false,
	"trimmed": false,
	"spriteSourceSize": {"x":0,"y":0,"w":70,"h":31},
	"sourceSize": {"w":70,"h":31},
	"pivot": {"x":0.5,"y":0.5}
},
"KillZoneStatic0010.png":
{
	"frame": {"x":146,"y":2,"w":70,"h":31},
	"rotated": false,
	"trimmed": false,
	"spriteSourceSize": {"x":0,"y":0,"w":70,"h":31},
	"sourceSize": {"w":70,"h":31},
	"pivot": {"x":0.5,"y":0.5}
},
"KillZoneStatic0014.png":
{
	"frame": {"x":218,"y":2,"w":70,"h":31},
	"rotated": false,
	"trimmed": false,
	"spriteSourceSize": {"x":0,"y":0,"w":70,"h":31},
	"sourceSize": {"w":70,"h":31},
	"pivot": {"x":0.5,"y":0.5}
},
"KillZoneStatic0015.png":
{
	"frame": {"x":218,"y":2,"w":70,"h":31},
	"rotated": false,
	"trimmed": false,
	"spriteSourceSize": {"x":0,"y":0,"w":70,"h":31},
	"sourceSize": {"w":70,"h":31},
	"pivot": {"x":0.5,"y":0.5}
},
"KillZoneStatic0011.png":
{
	"frame": {"x":290,"y":2,"w":70,"h":31},
	"rotated": false,
	"trimmed": false,
	"spriteSourceSize": {"x":0,"y":0,"w":70,"h":31},
	"sourceSize": {"w":70,"h":31},
	"pivot": {"x":0.5,"y":0.5}
},
"KillZoneStatic0012.png":
{
	"frame": {"x":290,"y":2,"w":70,"h":31},
	"rotated": false,
	"trimmed": false,
	"spriteSourceSize": {"x":0,"y":0,"w":70,"h":31},
	"sourceSize": {"w":70,"h":31},
	"pivot": {"x":0.5,"y":0.5}
},
"KillZoneStatic0013.png":
{
	"frame": {"x":290,"y":2,"w":70,"h":31},
	"rotated": false,
	"trimmed": false,
	"spriteSourceSize": {"x":0,"y":0,"w":70,"h":31},
	"sourceSize": {"w":70,"h":31},
	"pivot": {"x":0.5,"y":0.5}
},
"KillZoneStatic0006.png":
{
	"frame": {"x":362,"y":2,"w":70,"h":31},
	"rotated": false,
	"trimmed": false,
	"spriteSourceSize": {"x":0,"y":0,"w":70,"h":31},
	"sourceSize": {"w":70,"h":31},
	"pivot": {"x":0.5,"y":0.5}
},
"KillZoneStatic0007.png":
{
	"frame": {"x":362,"y":2,"w":70,"h":31},
	"rotated": false,
	"trimmed": false,
	"spriteSourceSize": {"x":0,"y":0,"w":70,"h":31},
	"sourceSize": {"w":70,"h":31},
	"pivot": {"x":0.5,"y":0.5}
},
"KillZoneStatic0008.png":
{
	"frame": {"x":362,"y":2,"w":70,"h":31},
	"rotated": false,
	"trimmed": false,
	"spriteSourceSize": {"x":0,"y":0,"w":70,"h":31},
	"sourceSize": {"w":70,"h":31},
	"pivot": {"x":0.5,"y":0.5}
},
"Collectable.png":
{
	"frame": {"x":434,"y":2,"w":37,"h":37},
	"rotated": false,
	"trimmed": false,
	"spriteSourceSize": {"x":0,"y":0,"w":37,"h":37},
	"sourceSize": {"w":37,"h":37},
	"pivot": {"x":0.5,"y":0.5}
},
"Collectable_ghost.png":
{
	"frame": {"x":473,"y":2,"w":37,"h":37},
	"rotated": false,
	"trimmed": false,
	"spriteSourceSize": {"x":0,"y":0,"w":37,"h":37},
	"sourceSize": {"w":37,"h":37},
	"pivot": {"x":0.5,"y":0.5}
},
"Platform1.png":
{
	"frame": {"x":2,"y":41,"w":175,"h":53},
	"rotated": false,
	"trimmed": false,
	"spriteSourceSize": {"x":0,"y":0,"w":175,"h":53},
	"sourceSize": {"w":175,"h":53},
	"pivot": {"x":0.5,"y":0.5}
},
"Platform0.png":
{
	"frame": {"x":179,"y":41,"w":105,"h":53},
	"rotated": false,
	"trimmed": false,
	"spriteSourceSize": {"x":0,"y":0,"w":105,"h":53},
	"sourceSize": {"w":105,"h":53},
	"pivot": {"x":0.5,"y":0.5}
},
"CheckPoint.png":
{
	"frame": {"x":286,"y":41,"w":25,"h":60},
	"rotated": false,
	"trimmed": false,
	"spriteSourceSize": {"x":0,"y":0,"w":25,"h":60},
	"sourceSize": {"w":25,"h":60},
	"pivot": {"x":0.5,"y":0.5}
},
"CheckPoint_used.png":
{
	"frame": {"x":313,"y":41,"w":25,"h":60},
	"rotated": false,
	"trimmed": false,
	"spriteSourceSize": {"x":0,"y":0,"w":25,"h":60},
	"sourceSize": {"w":25,"h":60},
	"pivot": {"x":0.5,"y":0.5}
},
"KillZoneDynamic.png":
{
	"frame": {"x":340,"y":41,"w":61,"h":61},
	"rotated": false,
	"trimmed": false,
	"spriteSourceSize": {"x":0,"y":0,"w":61,"h":61},
	"sourceSize": {"w":61,"h":61},
	"pivot": {"x":0.5,"y":0.5}
},
"Wall0.png":
{
	"frame": {"x":403,"y":41,"w":70,"h":70},
	"rotated": false,
	"trimmed": false,
	"spriteSourceSize": {"x":0,"y":0,"w":70,"h":70},
	"sourceSize": {"w":70,"h":70},
	"pivot": {"x":0.5,"y":0.5}
},
"BridgeLeft.png":
{
	"frame": {"x":2,"y":113,"w":88,"h":88},
	"rotated": false,
	"trimmed": false,
	"spriteSourceSize": {"x":0,"y":0,"w":88,"h":88},
	"sourceSize": {"w":88,"h":88},
	"pivot": {"x":0.5,"y":0.5}
},
"BridgeRight.png":
{
	"frame": {"x":92,"y":113,"w":88,"h":88},
	"rotated": false,
	"trimmed": false,
	"spriteSourceSize": {"x":0,"y":0,"w":88,"h":88},
	"sourceSize": {"w":88,"h":88},
	"pivot": {"x":0.5,"y":0.5}
},
"Destructible.png":
{
	"frame": {"x":182,"y":113,"w":105,"h":105},
	"rotated": false,
	"trimmed": false,
	"spriteSourceSize": {"x":0,"y":0,"w":105,"h":105},
	"sourceSize": {"w":105,"h":105},
	"pivot": {"x":0.5,"y":0.5}
},
"Wall1.png":
{
	"frame": {"x":289,"y":113,"w":175,"h":123},
	"rotated": false,
	"trimmed": false,
	"spriteSourceSize": {"x":0,"y":0,"w":175,"h":123},
	"sourceSize": {"w":175,"h":123},
	"pivot": {"x":0.5,"y":0.5}
},
"Wall2.png":
{
	"frame": {"x":2,"y":238,"w":315,"h":123},
	"rotated": false,
	"trimmed": false,
	"spriteSourceSize": {"x":0,"y":0,"w":315,"h":123},
	"sourceSize": {"w":315,"h":123},
	"pivot": {"x":0.5,"y":0.5}
},
"LimitLeft.png":
{
	"frame": {"x":319,"y":238,"w":158,"h":140},
	"rotated": false,
	"trimmed": false,
	"spriteSourceSize": {"x":0,"y":0,"w":158,"h":140},
	"sourceSize": {"w":158,"h":140},
	"pivot": {"x":0.5,"y":0.5}
},
"Wall3.png":
{
	"frame": {"x":2,"y":380,"w":140,"h":140},
	"rotated": false,
	"trimmed": false,
	"spriteSourceSize": {"x":0,"y":0,"w":140,"h":140},
	"sourceSize": {"w":140,"h":140},
	"pivot": {"x":0.5,"y":0.5}
},
"LimitRight.png":
{
	"frame": {"x":144,"y":380,"w":140,"h":140},
	"rotated": false,
	"trimmed": false,
	"spriteSourceSize": {"x":0,"y":0,"w":140,"h":140},
	"sourceSize": {"w":140,"h":140},
	"pivot": {"x":0.5,"y":0.5}
},
"Ground.png":
{
	"frame": {"x":286,"y":380,"w":140,"h":142},
	"rotated": false,
	"trimmed": false,
	"spriteSourceSize": {"x":0,"y":0,"w":140,"h":142},
	"sourceSize": {"w":140,"h":142},
	"pivot": {"x":0.5,"y":0.5}
}},
"meta": {
	"app": "http://www.codeandweb.com/texturepacker",
	"version": "1.0",
	"image": "decor_graphics.png",
	"format": "RGBA8888",
	"size": {"w":512,"h":524},
	"scale": "1",
	"smartupdate": "$TexturePacker:SmartUpdate:f866fddb6965e8a817b7841414df3689:cdbaf61aabb3bbd03f81fd149abfde16:2c5c4d4df6c539f1635c92a1609ba10f$"
}
}
